{
  "requestsFinished": 1,
  "requestsFailed": 0,
  "requestsRetries": 0,
  "requestsFailedPerMinute": 0,
  "requestsFinishedPerMinute": 21,
  "requestMinDurationMillis": 2701,
  "requestMaxDurationMillis": 2701,
  "requestTotalFailedDurationMillis": 0,
  "requestTotalFinishedDurationMillis": 2701,
  "crawlerStartedAt": "2025-05-18T13:16:37.749Z",
  "crawlerFinishedAt": "2025-05-18T13:16:40.582Z",
  "statsPersistedAt": "2025-05-18T13:16:40.582Z",
  "crawlerRuntimeMillis": 2913,
  "crawlerLastStartTimestamp": 1747574197669,
  "requestRetryHistogram": [
    1
  ],
  "statsId": 1,
  "requestAvgFailedDurationMillis": null,
  "requestAvgFinishedDurationMillis": 2701,
  "requestTotalDurationMillis": 2701,
  "requestsTotal": 1,
  "requestsWithStatusCode": {},
  "errors": {},
  "retryErrors": {}
}